zenoti/__init__.py
zenoti-0.2.8.dist-info/METADATA
zenoti-0.2.8.dist-info/WHEEL
zenoti-0.2.8.dist-info/RECORD
